UART/source/transmitter.v
//////////////////////////////////////////////////////////////////////
// Author: Russell Merrick
//////////////////////////////////////////////////////////////////////
// This file contains the UART Transmitter.  This transmitter is able
// to transmit 8 bits of serial data, one start bit, one stop bit,
// and no parity bit.  When transmit is complete o_Tx_done will be
// driven high for one clock cycle.
//
// Set Parameter CLKS_PER_BIT as follows:
// CLKS_PER_BIT = (Frequency of i_Clock)/(Frequency of UART)
// Example: 25 MHz Clock, 115200 baud UART
// (25000000)/(115200) = 217
 
module UART_TX 
  (
   input       i_Rst_L,
   input       i_Clock,
   input       i_TX_DV,
   input [7:0] i_TX_Byte, 
   input [15:0] CLKS_PER_BIT,
   output reg  o_TX_Active,
   output reg  o_TX_Serial,
   output reg  o_TX_Done
   );
 
  localparam IDLE         = 2'b00;
  localparam TX_START_BIT = 2'b01;
  localparam TX_DATA_BITS = 2'b10;
  localparam TX_STOP_BIT  = 2'b11;
  
  reg [2:0] r_SM_Main;
  reg [15:0] r_Clock_Count;
  reg [2:0] r_Bit_Index;
  reg [7:0] r_TX_Data;


  // Purpose: Control TX state machine
  always @(posedge i_Clock or negedge i_Rst_L)
  begin
    if (~i_Rst_L)
    begin
      r_SM_Main <= 3'b000;
	  o_TX_Active <= 1'b0;
	  o_TX_Serial <= 1'b1;
	  o_TX_Done <= 1'b0;
    end
    else
    begin

      o_TX_Done <= 1'b0;

      case (r_SM_Main)
      IDLE :
        begin
          o_TX_Serial   <= 1'b1;         // Drive Line High for Idle
          r_Clock_Count <= 0;
          r_Bit_Index   <= 0;
          
          if (i_TX_DV == 1'b1)
          begin
            o_TX_Active <= 1'b1;
            r_TX_Data   <= i_TX_Byte;
            r_SM_Main   <= TX_START_BIT;
          end
          else
            r_SM_Main <= IDLE;
        end // case: IDLE
      
      
      // Send out Start Bit. Start bit = 0
      TX_START_BIT :
        begin
          o_TX_Serial <= 1'b0;
          
          // Wait CLKS_PER_BIT-1 clock cycles for start bit to finish
          if (r_Clock_Count < CLKS_PER_BIT-1)
          begin
            r_Clock_Count <= r_Clock_Count + 1;
            r_SM_Main     <= TX_START_BIT;
          end
          else
          begin
            r_Clock_Count <= 0;
            r_SM_Main     <= TX_DATA_BITS;
          end
        end // case: TX_START_BIT
      
      
      // Wait CLKS_PER_BIT-1 clock cycles for data bits to finish         
      TX_DATA_BITS :
        begin
          o_TX_Serial <= r_TX_Data[r_Bit_Index];
          
          if (r_Clock_Count < CLKS_PER_BIT-1)
          begin
            r_Clock_Count <= r_Clock_Count + 1;
            r_SM_Main     <= TX_DATA_BITS;
          end
          else
          begin
            r_Clock_Count <= 0;
            
            // Check if we have sent out all bits
            if (r_Bit_Index < 7)
            begin
              r_Bit_Index <= r_Bit_Index + 1;
              r_SM_Main   <= TX_DATA_BITS;
            end
            else
            begin
              r_Bit_Index <= 0;
              r_SM_Main   <= TX_STOP_BIT;
            end
          end 
        end // case: TX_DATA_BITS
      
      
      // Send out Stop bit.  Stop bit = 1
      TX_STOP_BIT :
        begin
          o_TX_Serial <= 1'b1;
          
          // Wait CLKS_PER_BIT-1 clock cycles for Stop bit to finish
          if (r_Clock_Count < CLKS_PER_BIT-1)
          begin
            r_Clock_Count <= r_Clock_Count + 1;
            r_SM_Main     <= TX_STOP_BIT;
          end
          else
          begin
            o_TX_Done     <= 1'b1;
            r_Clock_Count <= 0;
            r_SM_Main     <= IDLE;
            o_TX_Active   <= 1'b0;
          end 
        end // case: TX_STOP_BIT      
      
      default :
        r_SM_Main <= IDLE;
      
    endcase
    end // else: !if(~i_Rst_L)
  end // always @ (posedge i_Clock or negedge i_Rst_L)

  
endmodule

UART/source/receiver.v
//////////////////////////////////////////////////////////////////////
// File Downloaded from http://www.nandland.com
//////////////////////////////////////////////////////////////////////
// This file contains the UART Receiver.  This receiver is able to
// receive 8 bits of serial data, one start bit, one stop bit,
// and no parity bit.  When receive is complete o_rx_dv will be
// driven high for one clock cycle.
// 
// Set Parameter CLKS_PER_BIT as follows:
// CLKS_PER_BIT = (Frequency of i_Clock)/(Frequency of UART)
// Example: 25 MHz Clock, 115200 baud UART
// (25000000)/(115200) = 217
 
module UART_RX
  (
   input        i_Clock,
   input        i_RX_Serial,
   input [15:0] CLKS_PER_BIT,
   output       o_RX_DV,
   output [7:0] o_RX_Byte
   );
   
  parameter IDLE         = 3'b000;
  parameter RX_START_BIT = 3'b001;
  parameter RX_DATA_BITS = 3'b010;
  parameter RX_STOP_BIT  = 3'b011;
  parameter CLEANUP      = 3'b100;
  
  reg [15:0] r_Clock_Count = 0;
  reg [2:0] r_Bit_Index   = 0; //8 bits total
  reg [7:0] r_RX_Byte     = 0;
  reg       r_RX_DV       = 0;
  reg [2:0] r_SM_Main     = 0;
  
  
  // Purpose: Control RX state machine
  always @(posedge i_Clock)
  begin
      
    case (r_SM_Main)
      IDLE :
        begin
          r_RX_DV       <= 1'b0;
          r_Clock_Count <= 0;
          r_Bit_Index   <= 0;
          
          if (i_RX_Serial == 1'b0)          // Start bit detected
            r_SM_Main <= RX_START_BIT;
          else
            r_SM_Main <= IDLE;
        end
      
      // Check middle of start bit to make sure it's still low
      RX_START_BIT :
        begin
          if (r_Clock_Count == (CLKS_PER_BIT-1)/2)
          begin
            if (i_RX_Serial == 1'b0)
            begin
              r_Clock_Count <= 0;  // reset counter, found the middle
              r_SM_Main     <= RX_DATA_BITS;
            end
            else
              r_SM_Main <= IDLE;
          end
          else
          begin
            r_Clock_Count <= r_Clock_Count + 1;
            r_SM_Main     <= RX_START_BIT;
          end
        end // case: RX_START_BIT
      
      
      // Wait CLKS_PER_BIT-1 clock cycles to sample serial data
      RX_DATA_BITS :
        begin
          if (r_Clock_Count < CLKS_PER_BIT-1)
          begin
            r_Clock_Count <= r_Clock_Count + 1;
            r_SM_Main     <= RX_DATA_BITS;
          end
          else
          begin
            r_Clock_Count          <= 0;
            r_RX_Byte[r_Bit_Index] <= i_RX_Serial;
            
            // Check if we have received all bits
            if (r_Bit_Index < 7)
            begin
              r_Bit_Index <= r_Bit_Index + 1;
              r_SM_Main   <= RX_DATA_BITS;
            end
            else
            begin
              r_Bit_Index <= 0;
              r_SM_Main   <= RX_STOP_BIT;
            end
          end
        end // case: RX_DATA_BITS
      
      
      // Receive Stop bit.  Stop bit = 1
      RX_STOP_BIT :
        begin
          // Wait CLKS_PER_BIT-1 clock cycles for Stop bit to finish
          if (r_Clock_Count < CLKS_PER_BIT-1)
          begin
            r_Clock_Count <= r_Clock_Count + 1;
     	    r_SM_Main     <= RX_STOP_BIT;
          end
          else
          begin
       	    r_RX_DV       <= 1'b1;
            r_Clock_Count <= 0;
            r_SM_Main     <= CLEANUP;
          end
        end // case: RX_STOP_BIT
      
      
      // Stay here 1 clock
      CLEANUP :
        begin
          r_SM_Main <= IDLE;
          r_RX_DV   <= 1'b0;
        end
      
      
      default :
        r_SM_Main <= IDLE;
      
    endcase
  end    
  
  assign o_RX_DV   = r_RX_DV;
  assign o_RX_Byte = r_RX_Byte;
  
endmodule // UART_RX

UART/test/UARTComponentTests.v
//////////////////////////////////////////////////////////////////////
// File Downloaded from http://www.nandland.com
//////////////////////////////////////////////////////////////////////

// This testbench will exercise the UART RX.
// It sends out byte 0x37, and ensures the RX receives it correctly.
`timescale 1ns/10ps

module UARTComponentTests ();

  // Testbench uses a 25 MHz clock
  // Want to interface to 115200 baud UART
  // 25000000 / 115200 = 217 Clocks Per Bit.
  parameter c_CLOCK_PERIOD_NS = 40;
  parameter c_CLKS_PER_BIT    = 16'd217;
  parameter c_BIT_PERIOD      = 8600;
  
  reg r_Clock = 0;
  reg r_TX_DV = 0;
  wire w_TX_Active, w_UART_Line;
  wire w_TX_Serial;
  reg [7:0] r_TX_Byte = 0;
  wire [7:0] w_RX_Byte;
  reg i_Rst_L = 1;

  UART_RX UART_RX_Inst
    (.i_Clock(r_Clock),
     .i_RX_Serial(w_UART_Line),
     .o_RX_DV(w_RX_DV),
     .o_RX_Byte(w_RX_Byte),
	 .CLKS_PER_BIT(c_CLKS_PER_BIT)
     );
  
  UART_TX UART_TX_Inst
    (.i_Clock(r_Clock),
	 .i_Rst_L(i_Rst_L),
     .i_TX_DV(r_TX_DV),
     .i_TX_Byte(r_TX_Byte),
     .o_TX_Active(w_TX_Active),
     .o_TX_Serial(w_TX_Serial),
     .o_TX_Done(),
	 .CLKS_PER_BIT(c_CLKS_PER_BIT)
 );

  // Keeps the UART Receive input high (default) when
  // UART transmitter is not active
  assign w_UART_Line = w_TX_Active ? w_TX_Serial : 1'b1;
    
  always
    #(c_CLOCK_PERIOD_NS/2) r_Clock <= !r_Clock;
  
  // Main Testing:
  initial
    begin
      // Tell UART to send a command (exercise TX)
      @(posedge r_Clock);
      @(posedge r_Clock);
      r_TX_DV   <= 1'b1;
      r_TX_Byte <= 8'h3F;
      @(posedge r_Clock);
      r_TX_DV <= 1'b0;

      // Check that the correct command was received
      @(posedge w_RX_DV);
      if (w_RX_Byte == 8'h3F)
        $display("Test Passed - Correct Byte Received");
      else
        $display("Test Failed - Incorrect Byte Received");
      $finish();
    end
  
  initial 
  begin
    // Required to dump signals to EPWave
    $dumpfile("dump.vcd");
    $dumpvars(0);
  end
endmodule

UART/test/UARTComponentsTestbench/dump.vcd
$date
	Fri Nov 03 13:40:46 2023
$end
$version
	ModelSim Version 2020.3
$end
$timescale
	10ps
$end

$scope module UARTComponentTests $end
$var parameter 32 ! c_CLOCK_PERIOD_NS $end
$var parameter 16 " c_CLKS_PER_BIT $end
$var parameter 32 # c_BIT_PERIOD $end
$var reg 1 $ r_Clock $end
$var reg 1 % r_TX_DV $end
$var wire 1 & w_TX_Active $end
$var wire 1 ' w_UART_Line $end
$var wire 1 ( w_TX_Serial $end
$var reg 8 ) r_TX_Byte [7:0] $end
$var wire 1 * w_RX_Byte [7] $end
$var wire 1 + w_RX_Byte [6] $end
$var wire 1 , w_RX_Byte [5] $end
$var wire 1 - w_RX_Byte [4] $end
$var wire 1 . w_RX_Byte [3] $end
$var wire 1 / w_RX_Byte [2] $end
$var wire 1 0 w_RX_Byte [1] $end
$var wire 1 1 w_RX_Byte [0] $end
$var reg 1 2 i_Rst_L $end
$var wire 1 3 w_RX_DV $end

$scope module UART_RX_Inst $end
$var parameter 3 4 IDLE $end
$var parameter 3 5 RX_START_BIT $end
$var parameter 3 6 RX_DATA_BITS $end
$var parameter 3 7 RX_STOP_BIT $end
$var parameter 3 8 CLEANUP $end
$var wire 1 9 i_Clock $end
$var wire 1 ' i_RX_Serial $end
$var wire 1 : CLKS_PER_BIT [15] $end
$var wire 1 ; CLKS_PER_BIT [14] $end
$var wire 1 < CLKS_PER_BIT [13] $end
$var wire 1 = CLKS_PER_BIT [12] $end
$var wire 1 > CLKS_PER_BIT [11] $end
$var wire 1 ? CLKS_PER_BIT [10] $end
$var wire 1 @ CLKS_PER_BIT [9] $end
$var wire 1 A CLKS_PER_BIT [8] $end
$var wire 1 B CLKS_PER_BIT [7] $end
$var wire 1 C CLKS_PER_BIT [6] $end
$var wire 1 D CLKS_PER_BIT [5] $end
$var wire 1 E CLKS_PER_BIT [4] $end
$var wire 1 F CLKS_PER_BIT [3] $end
$var wire 1 G CLKS_PER_BIT [2] $end
$var wire 1 H CLKS_PER_BIT [1] $end
$var wire 1 I CLKS_PER_BIT [0] $end
$var wire 1 3 o_RX_DV $end
$var wire 1 * o_RX_Byte [7] $end
$var wire 1 + o_RX_Byte [6] $end
$var wire 1 , o_RX_Byte [5] $end
$var wire 1 - o_RX_Byte [4] $end
$var wire 1 . o_RX_Byte [3] $end
$var wire 1 / o_RX_Byte [2] $end
$var wire 1 0 o_RX_Byte [1] $end
$var wire 1 1 o_RX_Byte [0] $end
$var reg 16 J r_Clock_Count [15:0] $end
$var reg 3 K r_Bit_Index [2:0] $end
$var reg 8 L r_RX_Byte [7:0] $end
$var reg 1 M r_RX_DV $end
$var reg 3 N r_SM_Main [2:0] $end
$upscope $end

$scope module UART_TX_Inst $end
$var parameter 2 O IDLE $end
$var parameter 2 P TX_START_BIT $end
$var parameter 2 Q TX_DATA_BITS $end
$var parameter 2 R TX_STOP_BIT $end
$var wire 1 S i_Rst_L $end
$var wire 1 T i_Clock $end
$var wire 1 U i_TX_DV $end
$var wire 1 V i_TX_Byte [7] $end
$var wire 1 W i_TX_Byte [6] $end
$var wire 1 X i_TX_Byte [5] $end
$var wire 1 Y i_TX_Byte [4] $end
$var wire 1 Z i_TX_Byte [3] $end
$var wire 1 [ i_TX_Byte [2] $end
$var wire 1 \ i_TX_Byte [1] $end
$var wire 1 ] i_TX_Byte [0] $end
$var wire 1 ^ CLKS_PER_BIT [15] $end
$var wire 1 _ CLKS_PER_BIT [14] $end
$var wire 1 ` CLKS_PER_BIT [13] $end
$var wire 1 a CLKS_PER_BIT [12] $end
$var wire 1 b CLKS_PER_BIT [11] $end
$var wire 1 c CLKS_PER_BIT [10] $end
$var wire 1 d CLKS_PER_BIT [9] $end
$var wire 1 e CLKS_PER_BIT [8] $end
$var wire 1 f CLKS_PER_BIT [7] $end
$var wire 1 g CLKS_PER_BIT [6] $end
$var wire 1 h CLKS_PER_BIT [5] $end
$var wire 1 i CLKS_PER_BIT [4] $end
$var wire 1 j CLKS_PER_BIT [3] $end
$var wire 1 k CLKS_PER_BIT [2] $end
$var wire 1 l CLKS_PER_BIT [1] $end
$var wire 1 m CLKS_PER_BIT [0] $end
$var reg 1 n o_TX_Active $end
$var reg 1 o o_TX_Serial $end
$var reg 1 p o_TX_Done $end
$var reg 3 q r_SM_Main [2:0] $end
$var reg 16 r r_Clock_Count [15:0] $end
$var reg 3 s r_Bit_Index [2:0] $end
$var reg 8 t r_TX_Data [7:0] $end
$upscope $end
$upscope $end
$enddefinitions $end
#0
$dumpvars
0$
0%
b0 )
12
b0 J
b0 K
b0 L
0M
b0 N
xn
xo
xp
bx q
bx r
bx s
bx t
b101000 !
b11011001 "
b10000110011000 #
b0 4
b1 5
b10 6
b11 7
b100 8
b0 O
b1 P
b10 Q
b11 R
x&
x'
x(
01
00
0/
0.
0-
0,
0+
0*
03
0]
0\
0[
0Z
0Y
0X
0W
0V
0U
1S
0T
09
1I
0H
0G
1F
1E
0D
1C
1B
0A
0@
0?
0>
0=
0<
0;
0:
1m
0l
0k
1j
1i
0h
1g
1f
0e
0d
0c
0b
0a
0`
0_
0^
$end
#2000
1$
19
1T
0p
b0 q
#4000
0$
09
0T
#6000
1$
19
1T
1o
b0 r
b0 s
1%
b111111 )
1(
1U
1]
1\
1[
1Z
1Y
1X
1'
#8000
0$
09
0T
#10000
1$
19
1T
1n
b111111 t
b1 q
0%
1&
0U
#12000
0$
09
0T
#14000
1$
19
1T
0o
b1 r
0(
0'
#16000
0$
09
0T
#18000
1$
19
1T
b10 r
b1 N
#20000
0$
09
0T
#22000
1$
19
1T
b11 r
b1 J
#24000
0$
09
0T
#26000
1$
19
1T
b100 r
b10 J
#28000
0$
09
0T
#30000
1$
19
1T
b101 r
b11 J
#32000
0$
09
0T
#34000
1$
19
1T
b110 r
b100 J
#36000
0$
09
0T
#38000
1$
19
1T
b111 r
b101 J
#40000
0$
09
0T
#42000
1$
19
1T
b1000 r
b110 J
#44000
0$
09
0T
#46000
1$
19
1T
b1001 r
b111 J
#48000
0$
09
0T
#50000
1$
19
1T
b1010 r
b1000 J
#52000
0$
09
0T
#54000
1$
19
1T
b1011 r
b1001 J
#56000
0$
09
0T
#58000
1$
19
1T
b1100 r
b1010 J
#60000
0$
09
0T
#62000
1$
19
1T
b1101 r
b1011 J
#64000
0$
09
0T
#66000
1$
19
1T
b1110 r
b1100 J
#68000
0$
09
0T
#70000
1$
19
1T
b1111 r
b1101 J
#72000
0$
09
0T
#74000
1$
19
1T
b10000 r
b1110 J
#76000
0$
09
0T
#78000
1$
19
1T
b10001 r
b1111 J
#80000
0$
09
0T
#82000
1$
19
1T
b10010 r
b10000 J
#84000
0$
09
0T
#86000
1$
19
1T
b10011 r
b10001 J
#88000
0$
09
0T
#90000
1$
19
1T
b10100 r
b10010 J
#92000
0$
09
0T
#94000
1$
19
1T
b10101 r
b10011 J
#96000
0$
09
0T
#98000
1$
19
1T
b10110 r
b10100 J
#100000
0$
09
0T
#102000
1$
19
1T
b10111 r
b10101 J
#104000
0$
09
0T
#106000
1$
19
1T
b11000 r
b10110 J
#108000
0$
09
0T
#110000
1$
19
1T
b11001 r
b10111 J
#112000
0$
09
0T
#114000
1$
19
1T
b11010 r
b11000 J
#116000
0$
09
0T
#118000
1$
19
1T
b11011 r
b11001 J
#120000
0$
09
0T
#122000
1$
19
1T
b11100 r
b11010 J
#124000
0$
09
0T
#126000
1$
19
1T
b11101 r
b11011 J
#128000
0$
09
0T
#130000
1$
19
1T
b11110 r
b11100 J
#132000
0$
09
0T
#134000
1$
19
1T
b11111 r
b11101 J
#136000
0$
09
0T
#138000
1$
19
1T
b100000 r
b11110 J
#140000
0$
09
0T
#142000
1$
19
1T
b100001 r
b11111 J
#144000
0$
09
0T
#146000
1$
19
1T
b100010 r
b100000 J
#148000
0$
09
0T
#150000
1$
19
1T
b100011 r
b100001 J
#152000
0$
09
0T
#154000
1$
19
1T
b100100 r
b100010 J
#156000
0$
09
0T
#158000
1$
19
1T
b100101 r
b100011 J
#160000
0$
09
0T
#162000
1$
19
1T
b100110 r
b100100 J
#164000
0$
09
0T
#166000
1$
19
1T
b100111 r
b100101 J
#168000
0$
09
0T
#170000
1$
19
1T
b101000 r
b100110 J
#172000
0$
09
0T
#174000
1$
19
1T
b101001 r
b100111 J
#176000
0$
09
0T
#178000
1$
19
1T
b101010 r
b101000 J
#180000
0$
09
0T
#182000
1$
19
1T
b101011 r
b101001 J
#184000
0$
09
0T
#186000
1$
19
1T
b101100 r
b101010 J
#188000
0$
09
0T
#190000
1$
19
1T
b101101 r
b101011 J
#192000
0$
09
0T
#194000
1$
19
1T
b101110 r
b101100 J
#196000
0$
09
0T
#198000
1$
19
1T
b101111 r
b101101 J
#200000
0$
09
0T
#202000
1$
19
1T
b110000 r
b101110 J
#204000
0$
09
0T
#206000
1$
19
1T
b110001 r
b101111 J
#208000
0$
09
0T
#210000
1$
19
1T
b110010 r
b110000 J
#212000
0$
09
0T
#214000
1$
19
1T
b110011 r
b110001 J
#216000
0$
09
0T
#218000
1$
19
1T
b110100 r
b110010 J
#220000
0$
09
0T
#222000
1$
19
1T
b110101 r
b110011 J
#224000
0$
09
0T
#226000
1$
19
1T
b110110 r
b110100 J
#228000
0$
09
0T
#230000
1$
19
1T
b110111 r
b110101 J
#232000
0$
09
0T
#234000
1$
19
1T
b111000 r
b110110 J
#236000
0$
09
0T
#238000
1$
19
1T
b111001 r
b110111 J
#240000
0$
09
0T
#242000
1$
19
1T
b111010 r
b111000 J
#244000
0$
09
0T
#246000
1$
19
1T
b111011 r
b111001 J
#248000
0$
09
0T
#250000
1$
19
1T
b111100 r
b111010 J
#252000
0$
09
0T
#254000
1$
19
1T
b111101 r
b111011 J
#256000
0$
09
0T
#258000
1$
19
1T
b111110 r
b111100 J
#260000
0$
09
0T
#262000
1$
19
1T
b111111 r
b111101 J
#264000
0$
09
0T
#266000
1$
19
1T
b1000000 r
b111110 J
#268000
0$
09
0T
#270000
1$
19
1T
b1000001 r
b111111 J
#272000
0$
09
0T
#274000
1$
19
1T
b1000010 r
b1000000 J
#276000
0$
09
0T
#278000
1$
19
1T
b1000011 r
b1000001 J
#280000
0$
09
0T
#282000
1$
19
1T
b1000100 r
b1000010 J
#284000
0$
09
0T
#286000
1$
19
1T
b1000101 r
b1000011 J
#288000
0$
09
0T
#290000
1$
19
1T
b1000110 r
b1000100 J
#292000
0$
09
0T
#294000
1$
19
1T
b1000111 r
b1000101 J
#296000
0$
09
0T
#298000
1$
19
1T
b1001000 r
b1000110 J
#300000
0$
09
0T
#302000
1$
19
1T
b1001001 r
b1000111 J
#304000
0$
09
0T
#306000
1$
19
1T
b1001010 r
b1001000 J
#308000
0$
09
0T
#310000
1$
19
1T
b1001011 r
b1001001 J
#312000
0$
09
0T
#314000
1$
19
1T
b1001100 r
b1001010 J
#316000
0$
09
0T
#318000
1$
19
1T
b1001101 r
b1001011 J
#320000
0$
09
0T
#322000
1$
19
1T
b1001110 r
b1001100 J
#324000
0$
09
0T
#326000
1$
19
1T
b1001111 r
b1001101 J
#328000
0$
09
0T
#330000
1$
19
1T
b1010000 r
b1001110 J
#332000
0$
09
0T
#334000
1$
19
1T
b1010001 r
b1001111 J
#336000
0$
09
0T
#338000
1$
19
1T
b1010010 r
b1010000 J
#340000
0$
09
0T
#342000
1$
19
1T
b1010011 r
b1010001 J
#344000
0$
09
0T
#346000
1$
19
1T
b1010100 r
b1010010 J
#348000
0$
09
0T
#350000
1$
19
1T
b1010101 r
b1010011 J
#352000
0$
09
0T
#354000
1$
19
1T
b1010110 r
b1010100 J
#356000
0$
09
0T
#358000
1$
19
1T
b1010111 r
b1010101 J
#360000
0$
09
0T
#362000
1$
19
1T
b1011000 r
b1010110 J
#364000
0$
09
0T
#366000
1$
19
1T
b1011001 r
b1010111 J
#368000
0$
09
0T
#370000
1$
19
1T
b1011010 r
b1011000 J
#372000
0$
09
0T
#374000
1$
19
1T
b1011011 r
b1011001 J
#376000
0$
09
0T
#378000
1$
19
1T
b1011100 r
b1011010 J
#380000
0$
09
0T
#382000
1$
19
1T
b1011101 r
b1011011 J
#384000
0$
09
0T
#386000
1$
19
1T
b1011110 r
b1011100 J
#388000
0$
09
0T
#390000
1$
19
1T
b1011111 r
b1011101 J
#392000
0$
09
0T
#394000
1$
19
1T
b1100000 r
b1011110 J
#396000
0$
09
0T
#398000
1$
19
1T
b1100001 r
b1011111 J
#400000
0$
09
0T
#402000
1$
19
1T
b1100010 r
b1100000 J
#404000
0$
09
0T
#406000
1$
19
1T
b1100011 r
b1100001 J
#408000
0$
09
0T
#410000
1$
19
1T
b1100100 r
b1100010 J
#412000
0$
09
0T
#414000
1$
19
1T
b1100101 r
b1100011 J
#416000
0$
09
0T
#418000
1$
19
1T
b1100110 r
b1100100 J
#420000
0$
09
0T
#422000
1$
19
1T
b1100111 r
b1100101 J
#424000
0$
09
0T
#426000
1$
19
1T
b1101000 r
b1100110 J
#428000
0$
09
0T
#430000
1$
19
1T
b1101001 r
b1100111 J
#432000
0$
09
0T
#434000
1$
19
1T
b1101010 r
b1101000 J
#436000
0$
09
0T
#438000
1$
19
1T
b1101011 r
b1101001 J
#440000
0$
09
0T
#442000
1$
19
1T
b1101100 r
b1101010 J
#444000
0$
09
0T
#446000
1$
19
1T
b1101101 r
b1101011 J
#448000
0$
09
0T
#450000
1$
19
1T
b1101110 r
b1101100 J
#452000
0$
09
0T
#454000
1$
19
1T
b1101111 r
b0 J
b10 N
#456000
0$
09
0T
#458000
1$
19
1T
b1110000 r
b1 J
#460000
0$
09
0T
#462000
1$
19
1T
b1110001 r
b10 J
#464000
0$
09
0T
#466000
1$
19
1T
b1110010 r
b11 J
#468000
0$
09
0T
#470000
1$
19
1T
b1110011 r
b100 J
#472000
0$
09
0T
#474000
1$
19
1T
b1110100 r
b101 J
#476000
0$
09
0T
#478000
1$
19
1T
b1110101 r
b110 J
#480000
0$
09
0T
#482000
1$
19
1T
b1110110 r
b111 J
#484000
0$
09
0T
#486000
1$
19
1T
b1110111 r
b1000 J
#488000
0$
09
0T
#490000
1$
19
1T
b1111000 r
b1001 J
#492000
0$
09
0T
#494000
1$
19
1T
b1111001 r
b1010 J
#496000
0$
09
0T
#498000
1$
19
1T
b1111010 r
b1011 J
#500000
0$
09
0T
#502000
1$
19
1T
b1111011 r
b1100 J
#504000
0$
09
0T
#506000
1$
19
1T
b1111100 r
b1101 J
#508000
0$
09
0T
#510000
1$
19
1T
b1111101 r
b1110 J
#512000
0$
09
0T
#514000
1$
19
1T
b1111110 r
b1111 J
#516000
0$
09
0T
#518000
1$
19
1T
b1111111 r
b10000 J
#520000
0$
09
0T
#522000
1$
19
1T
b10000000 r
b10001 J
#524000
0$
09
0T
#526000
1$
19
1T
b10000001 r
b10010 J
#528000
0$
09
0T
#530000
1$
19
1T
b10000010 r
b10011 J
#532000
0$
09
0T
#534000
1$
19
1T
b10000011 r
b10100 J
#536000
0$
09
0T
#538000
1$
19
1T
b10000100 r
b10101 J
#540000
0$
09
0T
#542000
1$
19
1T
b10000101 r
b10110 J
#544000
0$
09
0T
#546000
1$
19
1T
b10000110 r
b10111 J
#548000
0$
09
0T
#550000
1$
19
1T
b10000111 r
b11000 J
#552000
0$
09
0T
#554000
1$
19
1T
b10001000 r
b11001 J
#556000
0$
09
0T
#558000
1$
19
1T
b10001001 r
b11010 J
#560000
0$
09
0T
#562000
1$
19
1T
b10001010 r
b11011 J
#564000
0$
09
0T
#566000
1$
19
1T
b10001011 r
b11100 J
#568000
0$
09
0T
#570000
1$
19
1T
b10001100 r
b11101 J
#572000
0$
09
0T
#574000
1$
19
1T
b10001101 r
b11110 J
#576000
0$
09
0T
#578000
1$
19
1T
b10001110 r
b11111 J
#580000
0$
09
0T
#582000
1$
19
1T
b10001111 r
b100000 J
#584000
0$
09
0T
#586000
1$
19
1T
b10010000 r
b100001 J
#588000
0$
09
0T
#590000
1$
19
1T
b10010001 r
b100010 J
#592000
0$
09
0T
#594000
1$
19
1T
b10010010 r
b100011 J
#596000
0$
09
0T
#598000
1$
19
1T
b10010011 r
b100100 J
#600000
0$
09
0T
#602000
1$
19
1T
b10010100 r
b100101 J
#604000
0$
09
0T
#606000
1$
19
1T
b10010101 r
b100110 J
#608000
0$
09
0T
#610000
1$
19
1T
b10010110 r
b100111 J
#612000
0$
09
0T
#614000
1$
19
1T
b10010111 r
b101000 J
#616000
0$
09
0T
#618000
1$
19
1T
b10011000 r
b101001 J
#620000
0$
09
0T
#622000
1$
19
1T
b10011001 r
b101010 J
#624000
0$
09
0T
#626000
1$
19
1T
b10011010 r
b101011 J
#628000
0$
09
0T
#630000
1$
19
1T
b10011011 r
b101100 J
#632000
0$
09
0T
#634000
1$
19
1T
b10011100 r
b101101 J
#636000
0$
09
0T
#638000
1$
19
1T
b10011101 r
b101110 J
#640000
0$
09
0T
#642000
1$
19
1T
b10011110 r
b101111 J
#644000
0$
09
0T
#646000
1$
19
1T
b10011111 r
b110000 J
#648000
0$
09
0T
#650000
1$
19
1T
b10100000 r
b110001 J
#652000
0$
09
0T
#654000
1$
19
1T
b10100001 r
b110010 J
#656000
0$
09
0T
#658000
1$
19
1T
b10100010 r
b110011 J
#660000
0$
09
0T
#662000
1$
19
1T
b10100011 r
b110100 J
#664000
0$
09
0T
#666000
1$
19
1T
b10100100 r
b110101 J
#668000
0$
09
0T
#670000
1$
19
1T
b10100101 r
b110110 J
#672000
0$
09
0T
#674000
1$
19
1T
b10100110 r
b110111 J
#676000
0$
09
0T
#678000
1$
19
1T
b10100111 r
b111000 J
#680000
0$
09
0T
#682000
1$
19
1T
b10101000 r
b111001 J
#684000
0$
09
0T
#686000
1$
19
1T
b10101001 r
b111010 J
#688000
0$
09
0T
#690000
1$
19
1T
b10101010 r
b111011 J
#692000
0$
09
0T
#694000
1$
19
1T
b10101011 r
b111100 J
#696000
0$
09
0T
#698000
1$
19
1T
b10101100 r
b111101 J
#700000
0$
09
0T
#702000
1$
19
1T
b10101101 r
b111110 J
#704000
0$
09
0T
#706000
1$
19
1T
b10101110 r
b111111 J
#708000
0$
09
0T
#710000
1$
19
1T
b10101111 r
b1000000 J
#712000
0$
09
0T
#714000
1$
19
1T
b10110000 r
b1000001 J
#716000
0$
09
0T
#718000
1$
19
1T
b10110001 r
b1000010 J
#720000
0$
09
0T
#722000
1$
19
1T
b10110010 r
b1000011 J
#724000
0$
09
0T
#726000
1$
19
1T
b10110011 r
b1000100 J
#728000
0$
09
0T
#730000
1$
19
1T
b10110100 r
b1000101 J
#732000
0$
09
0T
#734000
1$
19
1T
b10110101 r
b1000110 J
#736000
0$
09
0T
#738000
1$
19
1T
b10110110 r
b1000111 J
#740000
0$
09
0T
#742000
1$
19
1T
b10110111 r
b1001000 J
#744000
0$
09
0T
#746000
1$
19
1T
b10111000 r
b1001001 J
#748000
0$
09
0T
#750000
1$
19
1T
b10111001 r
b1001010 J
#752000
0$
09
0T
#754000
1$
19
1T
b10111010 r
b1001011 J
#756000
0$
09
0T
#758000
1$
19
1T
b10111011 r
b1001100 J
#760000
0$
09
0T
#762000
1$
19
1T
b10111100 r
b1001101 J
#764000
0$
09
0T
#766000
1$
19
1T
b10111101 r
b1001110 J
#768000
0$
09
0T
#770000
1$
19
1T
b10111110 r
b1001111 J
#772000
0$
09
0T
#774000
1$
19
1T
b10111111 r
b1010000 J
#776000
0$
09
0T
#778000
1$
19
1T
b11000000 r
b1010001 J
#780000
0$
09
0T
#782000
1$
19
1T
b11000001 r
b1010010 J
#784000
0$
09
0T
#786000
1$
19
1T
b11000010 r
b1010011 J
#788000
0$
09
0T
#790000
1$
19
1T
b11000011 r
b1010100 J
#792000
0$
09
0T
#794000
1$
19
1T
b11000100 r
b1010101 J
#796000
0$
09
0T
#798000
1$
19
1T
b11000101 r
b1010110 J
#800000
0$
09
0T
#802000
1$
19
1T
b11000110 r
b1010111 J
#804000
0$
09
0T
#806000
1$
19
1T
b11000111 r
b1011000 J
#808000
0$
09
0T
#810000
1$
19
1T
b11001000 r
b1011001 J
#812000
0$
09
0T
#814000
1$
19
1T
b11001001 r
b1011010 J
#816000
0$
09
0T
#818000
1$
19
1T
b11001010 r
b1011011 J
#820000
0$
09
0T
#822000
1$
19
1T
b11001011 r
b1011100 J
#824000
0$
09
0T
#826000
1$
19
1T
b11001100 r
b1011101 J
#828000
0$
09
0T
#830000
1$
19
1T
b11001101 r
b1011110 J
#832000
0$
09
0T
#834000
1$
19
1T
b11001110 r
b1011111 J
